cloudshell/__init__.py
cloudshell/firewall/__init__.py
cloudshell/firewall/paloalto/__init__.py
cloudshell/firewall/paloalto/panos/__init__.py
cloudshell/firewall/paloalto/panos/autoload/__init__.py
cloudshell/firewall/paloalto/panos/autoload/panos_generic_snmp_autoload.py
cloudshell/firewall/paloalto/panos/autoload/panos_snmp_system_info.py
cloudshell/firewall/paloalto/panos/cli/__init__.py
cloudshell/firewall/paloalto/panos/cli/panos_cli_handler.py
cloudshell/firewall/paloalto/panos/cli/panos_command_modes.py
cloudshell/firewall/paloalto/panos/command_actions/__init__.py
cloudshell/firewall/paloalto/panos/command_actions/enable_disable_snmp_actions.py
cloudshell/firewall/paloalto/panos/command_actions/system_actions.py
cloudshell/firewall/paloalto/panos/command_templates/__init__.py
cloudshell/firewall/paloalto/panos/command_templates/configuration.py
cloudshell/firewall/paloalto/panos/command_templates/enable_disable_snmp.py
cloudshell/firewall/paloalto/panos/command_templates/firmware.py
cloudshell/firewall/paloalto/panos/flows/__init__.py
cloudshell/firewall/paloalto/panos/flows/panos_autoload_flow.py
cloudshell/firewall/paloalto/panos/flows/panos_configuration_flow.py
cloudshell/firewall/paloalto/panos/flows/panos_disable_snmp_flow.py
cloudshell/firewall/paloalto/panos/flows/panos_enable_snmp_flow.py
cloudshell/firewall/paloalto/panos/flows/panos_load_firmware_flow.py
cloudshell/firewall/paloalto/panos/flows/panos_run_command_flow.py
cloudshell/firewall/paloalto/panos/flows/panos_state_flow.py
cloudshell/firewall/paloalto/panos/helpers/__init__.py
cloudshell/firewall/paloalto/panos/helpers/temp_dir_context.py
cloudshell/firewall/paloalto/panos/mibs/PAN-COMMON-MIB.py
cloudshell/firewall/paloalto/panos/mibs/PAN-ENTITY-EXT-MIB.py
cloudshell/firewall/paloalto/panos/mibs/PAN-GLOBAL-REG.py
cloudshell/firewall/paloalto/panos/mibs/PAN-GLOBAL-TC.py
cloudshell/firewall/paloalto/panos/mibs/PAN-PRODUCTS-MIB.py
cloudshell/firewall/paloalto/panos/mibs/__init__.py
cloudshell_firewall_panos-2.0.1.dist-info/LICENSE.htm
cloudshell_firewall_panos-2.0.1.dist-info/METADATA
cloudshell_firewall_panos-2.0.1.dist-info/WHEEL
cloudshell_firewall_panos-2.0.1.dist-info/top_level.txt
cloudshell_firewall_panos-2.0.1.dist-info/RECORD
