Metadata-Version: 2.1
Name: cloudshell-firewall-panos
Version: 2.0.1
Summary: QualiSystems firewall Palo Alto PanOS specific Package
Home-page: http://www.qualisystems.com/
Author: QualiSystems
Author-email: info@qualisystems.com
License: UNKNOWN
Platform: UNKNOWN
Requires-Python: ~=3.7
License-File: LICENSE.htm
Requires-Dist: tftpy
Requires-Dist: cloudshell-shell-flows (<2.0,>=1.0.5)
Requires-Dist: cloudshell-snmp (<5.0,>=4.0)
Requires-Dist: cloudshell-snmp-autoload (<2.0,>=1.0)
Requires-Dist: cloudshell-cli (<5.0,>=4.0)
Requires-Dist: cloudshell-shell-standards (<2.0,>=1.2)
